db/__init__.py
db/db.py
griffin_db-0.1.7.dist-info/METADATA
griffin_db-0.1.7.dist-info/WHEEL
griffin_db-0.1.7.dist-info/top_level.txt
griffin_db-0.1.7.dist-info/RECORD
