Metadata-Version: 2.1
Name: griffin-db
Version: 0.1.7
Summary: A small wrapper for psycopg2 and queries with commonly used functions
Home-page: UNKNOWN
Author: Adrian Campos
Author-email: adrian@g4tv.com
License: UNKNOWN
Platform: UNKNOWN
Classifier: Programming Language :: Python :: 3
Classifier: Operating System :: OS Independent
Requires-Python: >=3.6
Requires-Dist: queries (~=2.1.0)
Requires-Dist: python-dotenv
